ingestor/__init__.py
ingestor/processors.py
ingestor_by_ckl-2.dist-info/METADATA
ingestor_by_ckl-2.dist-info/WHEEL
ingestor_by_ckl-2.dist-info/top_level.txt
ingestor_by_ckl-2.dist-info/RECORD
