Metadata-Version: 2.1
Name: ingestor_by_ckl
Version: 2
Summary: MLflow: A Platform for ML Development and Productionization
Home-page: UNKNOWN
Author: Databricks
License: Apache License 2.0
Platform: UNKNOWN
Classifier: Intended Audience :: Developers
Requires-Python: >=3.5
